.DS_Store
pybeads/__init__.py
pybeads-1.0.1.dist-info/LICENSE
pybeads-1.0.1.dist-info/METADATA
pybeads-1.0.1.dist-info/WHEEL
pybeads-1.0.1.dist-info/top_level.txt
pybeads-1.0.1.dist-info/RECORD
