Metadata-Version: 2.1
Name: pybeads
Version: 1.0.1
Summary: Baseline estimation and denoizing algorithm using sparcity
Home-page: https://github.com/skotaro/pybeads
Author: Kotaro Saito
Author-email: kotaro.saito@kek.jp
License: MIT
Keywords: beads baseline background
Platform: UNKNOWN
Classifier: License :: OSI Approved :: MIT License
Classifier: Programming Language :: Python :: 3.6
Classifier: Operating System :: OS Independent
Requires-Python: >=3.6
Requires-Dist: numpy
Requires-Dist: scipy
